oktacmd/__init__.py
oktacmd/__main__.py
oktacmd/cli.py
oktacmd/common.py
oktacmd/main.py
oktacmd/okta.py
okta_cmd-0.1.1.dist-info/LICENSE
okta_cmd-0.1.1.dist-info/METADATA
okta_cmd-0.1.1.dist-info/WHEEL
okta_cmd-0.1.1.dist-info/entry_points.txt
okta_cmd-0.1.1.dist-info/top_level.txt
okta_cmd-0.1.1.dist-info/RECORD
